[
  {
    "tag": "Button",
    "x1": 727,
    "y1": 0,
    "x2": 899,
    "y2": 72
  },
  {
    "tag": "Button",
    "x1": 899,
    "y1": 0,
    "x2": 1024,
    "y2": 72
  },
  {
    "tag": "Button",
    "x1": 1024,
    "y1": 0,
    "x2": 1140,
    "y2": 72
  },
  {
    "tag": "Button",
    "x1": 1140,
    "y1": 0,
    "x2": 1248,
    "y2": 72
  },
  {
    "tag": "Button",
    "x1": 1248,
    "y1": 0,
    "x2": 1343,
    "y2": 72
  },
  {
    "tag": "Button",
    "x1": 1343,
    "y1": 0,
    "x2": 1414,
    "y2": 72
  },
  {
    "tag": "Button",
    "x1": 1316,
    "y1": 22,
    "x2": 1414,
    "y2": 50
  },
  {
    "tag": "Button",
    "x1": 1424,
    "y1": 20,
    "x2": 1456,
    "y2": 52
  },
  {
    "tag": "Button",
    "x1": 1464,
    "y1": 20,
    "x2": 1496,
    "y2": 52
  },
  {
    "tag": "Button",
    "x1": 1504,
    "y1": 20,
    "x2": 1535,
    "y2": 52
  },
  {
    "tag": "Button",
    "x1": 1544,
    "y1": 20,
    "x2": 1576,
    "y2": 52
  },
  {
    "tag": "Button",
    "x1": 736,
    "y1": 693,
    "x2": 898,
    "y2": 733
  },
  {
    "tag": "Button",
    "x1": 898,
    "y1": 693,
    "x2": 1022,
    "y2": 733
  },
  {
    "tag": "Button",
    "x1": 1022,
    "y1": 693,
    "x2": 1183,
    "y2": 733
  },
  {
    "tag": "Button",
    "x1": 1398,
    "y1": 882,
    "x2": 1509,
    "y2": 919
  },
  {
    "tag": "Button",
    "x1": 1414,
    "y1": 882,
    "x2": 1510,
    "y2": 919
  },
  {
    "tag": "Button",
    "x1": 322,
    "y1": 860,
    "x2": 1598,
    "y2": 941
  },
  {
    "tag": "Button",
    "x1": 1562,
    "y1": 882,
    "x2": 1598,
    "y2": 919
  },
  {
    "tag": "Button",
    "x1": 1568,
    "y1": 888,
    "x2": 1592,
    "y2": 913
  },
  {
    "tag": "Button",
    "x1": 787,
    "y1": 573,
    "x2": 891,
    "y2": 589
  },
  {
    "tag": "Button",
    "x1": 907,
    "y1": 573,
    "x2": 1048,
    "y2": 589
  },
  {
    "tag": "Button",
    "x1": 1063,
    "y1": 573,
    "x2": 1132,
    "y2": 589
  }
]